document_catalogue/__init__.py
document_catalogue/admin.py
document_catalogue/apps.py
document_catalogue/decorators.py
document_catalogue/fields.py
document_catalogue/forms.py
document_catalogue/models.py
document_catalogue/permissions.py
document_catalogue/plugins.py
document_catalogue/settings.py
document_catalogue/urls.py
document_catalogue/views.py
document_catalogue/views_generic.py
document_catalogue/migrations/0001_initial.py
document_catalogue/migrations/0002_auto_20200522_2247.py
document_catalogue/migrations/__init__.py
document_catalogue/static/document_catalogue/document_catalogue.js
document_catalogue/templates/document_catalogue/base.html
document_catalogue/templates/document_catalogue/categories_list.html
document_catalogue/templates/document_catalogue/category_document_list.html
document_catalogue/templates/document_catalogue/document_confirm_delete.html
document_catalogue/templates/document_catalogue/document_detail.html
document_catalogue/templates/document_catalogue/document_edit.html
document_catalogue/templates/document_catalogue/ajax/document_item.html
document_catalogue/templates/document_catalogue/ajax/form_errors.html
document_catalogue/templates/document_catalogue/include/breadcrumb.html
document_catalogue/templates/document_catalogue/include/categories.html
document_catalogue/templates/document_catalogue/include/category-header.html
document_catalogue/templates/document_catalogue/include/doc_ordering.html
document_catalogue/templates/document_catalogue/include/doc_search.html
document_catalogue/templates/document_catalogue/include/document.html
document_catalogue/templates/document_catalogue/include/documents.html
document_catalogue/templates/document_catalogue/include/dropzone.html
document_catalogue/templates/document_catalogue/include/inline_clearable_file_input.html
document_catalogue/templatetags/__init__.py
document_catalogue/templatetags/form_tags.py
document_catalogue/templatetags/permissions_tags.py
django_document_catalogue-0.4.0.dist-info/AUTHORS
django_document_catalogue-0.4.0.dist-info/LICENSE
django_document_catalogue-0.4.0.dist-info/METADATA
django_document_catalogue-0.4.0.dist-info/WHEEL
django_document_catalogue-0.4.0.dist-info/entry_points.txt
django_document_catalogue-0.4.0.dist-info/top_level.txt
django_document_catalogue-0.4.0.dist-info/RECORD
