Metadata-Version: 2.1
Name: django-document-catalogue
Version: 0.4.0
Summary: A simple, lightweight, stand-alone, hierarchical document library as a reusable Django app.
Author-email: powderflask <powderflask@gmail.com>
License: MIT License
Project-URL: Homepage, https://github.com/powderflask/django_document_catalogue
Project-URL: Repository, https://github.com/powderflask/django_document_catalogue
Project-URL: Documentation, https://django-document-catalogue.readthedocs.io
Keywords: Django,Python
Classifier: Development Status :: 4 - Beta
Classifier: License :: OSI Approved :: MIT License
Classifier: Intended Audience :: Developers
Classifier: Natural Language :: English
Classifier: Programming Language :: Python :: 3
Classifier: Framework :: Django
Classifier: Environment :: Web Environment
Classifier: Operating System :: OS Independent
Requires-Python: <4,>=3.7
License-File: LICENSE
License-File: AUTHORS
Requires-Dist: Django <5.0,>=3.2
Requires-Dist: django-constrainedfilefield >=3.2.0
Requires-Dist: django-mptt >=0.10.0
Requires-Dist: python-magic >=0.4.15
Requires-Dist: django-private-storage >=2.2
Requires-Dist: django-admin-sortable2 <2.0,>=1.0
Provides-Extra: docs
Requires-Dist: sphinx ; extra == 'docs'
Requires-Dist: sphinx-rtd-theme ; extra == 'docs'
Requires-Dist: myst-parser ; extra == 'docs'
Provides-Extra: style
Requires-Dist: black ; extra == 'style'
Requires-Dist: isort ; extra == 'style'
Requires-Dist: flake8 ; extra == 'style'
Requires-Dist: flake8-bugbear ; extra == 'style'
Provides-Extra: test
Requires-Dist: tox ; extra == 'test'
Requires-Dist: pytest ; extra == 'test'
Requires-Dist: pytest-django ; extra == 'test'
Requires-Dist: pytest-cov ; extra == 'test'
Requires-Dist: pytest-sugar ; extra == 'test'
Provides-Extra: utils
Requires-Dist: django-debug-toolbar ; extra == 'utils'
Requires-Dist: invoke ; extra == 'utils'
Requires-Dist: bumpver ; extra == 'utils'
Requires-Dist: build ; extra == 'utils'
Requires-Dist: twine ; extra == 'utils'
